{
  "entities": {
    "User": {
      "title": "User",
      "description": "A user of the FlameGrilled app.",
      "type": "object",
      "properties": {
        "uid": { "type": "string", "description": "The unique ID of the user." },
        "email": { "type": "string", "format": "email", "description": "The user's email address." },
        "displayName": { "type": "string", "description": "The user's display name." },
        "photoURL": { "type": "string", "format": "uri", "description": "The user's profile photo URL." },
        "crowns": { "type": "integer", "description": "The user's loyalty points (crowns)." }
      },
      "required": ["uid", "email"]
    },
    "Order": {
      "title": "Order",
      "description": "A food order placed by a user.",
      "type": "object",
      "properties": {
        "id": { "type": "string", "description": "The unique ID of the order." },
        "userId": { "type": "string", "description": "The ID of the user who placed the order." },
        "items": { "type": "array", "items": { "type": "object" }, "description": "The items in the order." },
        "total": { "type": "number", "description": "The total cost of the order." },
        "status": { "type": "string", "enum": ["pending", "preparing", "ready", "delivered"], "description": "The status of the order." },
        "createdAt": { "type": "string", "format": "date-time", "description": "The time the order was placed." }
      },
      "required": ["userId", "items", "total", "status", "createdAt"]
    },
    "Reward": {
      "title": "Reward",
      "description": "A loyalty reward available to users.",
      "type": "object",
      "properties": {
        "id": { "type": "string", "description": "The unique ID of the reward." },
        "name": { "type": "string", "description": "The name of the reward." },
        "cost": { "type": "integer", "description": "The cost of the reward in crowns." },
        "description": { "type": "string", "description": "A description of the reward." }
      },
      "required": ["name", "cost"]
    }
  },
  "firestore": {
    "/users/{userId}": {
      "schema": "User",
      "description": "User profile data."
    },
    "/orders/{orderId}": {
      "schema": "Order",
      "description": "Order history data."
    },
    "/rewards/{rewardId}": {
      "schema": "Reward",
      "description": "Available loyalty rewards."
    }
  }
}
